wfield/__init__.py
wfield/allen.py
wfield/allen_utils.py
wfield/cli.py
wfield/dask.py
wfield/decomposition.py
wfield/hemocorrection.py
wfield/imutils.py
wfield/io.py
wfield/local_nmf.py
wfield/multisession.py
wfield/ncaas.py
wfield/ncaas_gui.py
wfield/ncaas_utils.py
wfield/plots.py
wfield/registration.py
wfield/utils.py
wfield/utils_svd.py
wfield/viz.py
wfield/widgets.py
wfield-0.6.0.dist-info/licenses/LICENSE.txt
wfield-0.6.0.dist-info/METADATA
wfield-0.6.0.dist-info/WHEEL
wfield-0.6.0.dist-info/entry_points.txt
wfield-0.6.0.dist-info/top_level.txt
wfield-0.6.0.dist-info/RECORD
