Metadata-Version: 2.4
Name: wfield
Version: 0.6.0
Summary: Utilities to look at widefield data and align with the allen reference map.
Home-page: https://github.com/jcouto/wfield
Author: Joao Couto
Author-email: jpcouto@gmail.com
License: GPL
License-File: LICENSE.txt
Requires-Dist: numpy
Requires-Dist: scipy
Requires-Dist: matplotlib
Requires-Dist: pims
Requires-Dist: pandas
Requires-Dist: tqdm
Requires-Dist: opencv-python-headless
Requires-Dist: tifffile
Requires-Dist: pyqt5
Requires-Dist: pyqtgraph
Requires-Dist: pillow
Requires-Dist: scikit-video
Requires-Dist: scikit-image
Requires-Dist: scikit-learn
Requires-Dist: pyserial
Requires-Dist: natsort
Requires-Dist: pyqtgraph
Requires-Dist: pyqtwebengine
Requires-Dist: boto3
Requires-Dist: pyyaml
Requires-Dist: requests
Requires-Dist: joblib
Dynamic: author
Dynamic: author-email
Dynamic: description
Dynamic: description-content-type
Dynamic: home-page
Dynamic: license
Dynamic: license-file
Dynamic: requires-dist
Dynamic: summary
